flask_ngrok2.py
flask_ngrok2-0.2.4.dist-info/LICENSE
flask_ngrok2-0.2.4.dist-info/METADATA
flask_ngrok2-0.2.4.dist-info/WHEEL
flask_ngrok2-0.2.4.dist-info/top_level.txt
flask_ngrok2-0.2.4.dist-info/RECORD
