Metadata-Version: 2.1
Name: flask-ngrok2
Version: 0.2.4
Summary: A successor to flask-ngrok for demo Flask apps using ngrok.
Home-page: https://github.com/MohamedAliRashad/flask-ngrok2
Author: Mohamed Rashad
Keywords: flask ngrok2 demo
Classifier: Programming Language :: Python :: 3.6
Classifier: License :: OSI Approved :: Apache Software License
Classifier: Operating System :: OS Independent
License-File: LICENSE
